[{
    "time": 5072,
    "timeup": false,
    "done": true,
    "player": "829247117065477",
    "stage": {
        "stage": 1,
        "step": 1,
        "round": 1
    },
    "timestamp": 1595481437174
}, {
    "time": 7030,
    "timeup": false,
    "done": true,
    "player": "115064535382691",
    "stage": {
        "stage": 1,
        "step": 1,
        "round": 1
    },
    "timestamp": 1595481439129
}, {
    "time": 3287,
    "timeup": false,
    "offer": 1,
    "done": true,
    "player": "829247117065477",
    "stage": {
        "stage": 2,
        "step": 1,
        "round": 1
    },
    "timestamp": 1595481442600
}, {
    "time": 8300,
    "timeup": false,
    "done": true,
    "player": "115064535382691",
    "stage": {
        "stage": 2,
        "step": 1,
        "round": 1
    },
    "timestamp": 1595481447618
}, {
    "time": 2644,
    "timeup": false,
    "offer": 2,
    "done": true,
    "player": "115064535382691",
    "stage": {
        "stage": 2,
        "step": 1,
        "round": 2
    },
    "timestamp": 1595481450466
}, {
    "time": 7647,
    "timeup": false,
    "done": true,
    "player": "829247117065477",
    "stage": {
        "stage": 2,
        "step": 1,
        "round": 2
    },
    "timestamp": 1595481455471
}, {
    "time": 8133,
    "timeup": false,
    "offer": 32,
    "done": true,
    "player": "829247117065477",
    "stage": {
        "stage": 2,
        "step": 1,
        "round": 3
    },
    "timestamp": 1595481463819
}, {
    "time": 13141,
    "timeup": false,
    "done": true,
    "player": "115064535382691",
    "stage": {
        "stage": 2,
        "step": 1,
        "round": 3
    },
    "timestamp": 1595481468829
}, {
    "time": 2342,
    "timeup": false,
    "offer": 33,
    "done": true,
    "player": "115064535382691",
    "stage": {
        "stage": 2,
        "step": 1,
        "round": 4
    },
    "timestamp": 1595481471352
}, {
    "time": 7350,
    "timeup": false,
    "done": true,
    "player": "829247117065477",
    "stage": {
        "stage": 2,
        "step": 1,
        "round": 4
    },
    "timestamp": 1595481476363
}]